arq_dashboard/__init__.py
arq_dashboard/api/__init__.py
arq_dashboard/api/api.py
arq_dashboard/api/endpoints/__init__.py
arq_dashboard/api/endpoints/functions.py
arq_dashboard/api/endpoints/jobs.py
arq_dashboard/api/endpoints/queues.py
arq_dashboard/api/endpoints/stats.py
arq_dashboard/core/__init__.py
arq_dashboard/core/datastructures.py
arq_dashboard/core/settings.py
arq_dashboard/dependencies.py
arq_dashboard/errors.py
arq_dashboard/frontend/assets/fa-brands-400.3fe890d0.woff2
arq_dashboard/frontend/assets/fa-brands-400.c7ae37d3.ttf
arq_dashboard/frontend/assets/fa-regular-400.fdc1f753.ttf
arq_dashboard/frontend/assets/fa-regular-400.fe69d948.woff2
arq_dashboard/frontend/assets/fa-solid-900.6d53c706.ttf
arq_dashboard/frontend/assets/fa-solid-900.d27bc752.woff2
arq_dashboard/frontend/assets/fa-v4compatibility.4d73f280.ttf
arq_dashboard/frontend/assets/fa-v4compatibility.7d1c2ce5.woff2
arq_dashboard/frontend/assets/index.5c3f7c7a.css
arq_dashboard/frontend/assets/index.86adf8cc.js
arq_dashboard/frontend/index.html
arq_dashboard/main.py
arq_dashboard/queue.py
arq_dashboard/schemas/__init__.py
arq_dashboard/schemas/api_model.py
arq_dashboard/schemas/function.py
arq_dashboard/schemas/job.py
arq_dashboard/schemas/mixins.py
arq_dashboard/schemas/queue.py
arq_dashboard/utils.py
arq_dashboard-0.1.4.dist-info/LICENSE
arq_dashboard-0.1.4.dist-info/WHEEL
arq_dashboard-0.1.4.dist-info/METADATA
arq_dashboard-0.1.4.dist-info/RECORD
