Metadata-Version: 2.1
Name: arq-dashboard
Version: 0.1.4
Summary: A dashboard for ARQ built with FastAPI
Home-page: https://github.com/ninoseki/arq-dashboard
License: MIT
Author: Manabu Niseki
Author-email: manabu.niseki@gmail.com
Requires-Python: >=3.8,<4.0
Classifier: License :: OSI Approved :: MIT License
Classifier: Programming Language :: Python :: 3
Classifier: Programming Language :: Python :: 3.10
Classifier: Programming Language :: Python :: 3.8
Classifier: Programming Language :: Python :: 3.9
Requires-Dist: aiometer (>=0.3.0,<0.4.0)
Requires-Dist: arq (>=0.24,<0.25)
Requires-Dist: arrow (>=1.2.3,<2.0.0)
Requires-Dist: async-cache (>=1.1.1,<2.0.0)
Requires-Dist: fastapi (>=0.85.1,<0.86.0)
Requires-Dist: loguru (>=0.6.0,<0.7.0)
Requires-Dist: pydantic (>=1.10.2,<2.0.0)
Requires-Dist: pyhumps (>=3.7.3,<4.0.0)
Requires-Dist: uvicorn[standard] (>=0.18.3,<0.19.0)
Project-URL: Repository, https://github.com/ninoseki/arq-dashboard
